psdaq/__init__.py
psdaq/_version.py
psdaq/control/BlueskyScan.py
psdaq/control/ConfigScan.py
psdaq/control/ControlDef.py
psdaq/control/DaqControl.py
psdaq/control/TimedRun.py
psdaq/control/__init__.py
psdaq/control/config_scan.py
psdaq/control/control.py
psdaq/control/currentexp.py
psdaq/control/daqstate.py
psdaq/control/epixquad_chargeinj_scan.py
psdaq/control/epixquad_pedestal_scan.py
psdaq/control/getrun.py
psdaq/control/lab3_bluesky_scan.py
psdaq/control/lab3_timed_run.py
psdaq/control/opal_config_scan.py
psdaq/control/rix_bluesky_scan.py
psdaq/control/rix_timed_run.py
psdaq/control/selectPlatform.py
psdaq/control/showPlatform.py
psdaq/control/testAsyncErr.py
psdaq/control/testClient2.py
psdaq/control/testFileReport.py
psdaq/control/ts_config_scan.py
psdaq_control_minimal-4.1.2.dist-info/AUTHORS.rst
psdaq_control_minimal-4.1.2.dist-info/LICENSE
psdaq_control_minimal-4.1.2.dist-info/METADATA
psdaq_control_minimal-4.1.2.dist-info/WHEEL
psdaq_control_minimal-4.1.2.dist-info/top_level.txt
psdaq_control_minimal-4.1.2.dist-info/RECORD
