Metadata-Version: 2.1
Name: psdaq-control-minimal
Version: 4.1.2
Summary: A minimal repackaging of the lcls2 daq control interface.
Author: SLAC National Accelerator Laboratory
Classifier: Development Status :: 5 - Production/Stable
Classifier: Natural Language :: English
Classifier: Programming Language :: Python :: 3
Requires-Python: >=3.6
License-File: LICENSE
License-File: AUTHORS.rst
Requires-Dist: bluesky
Requires-Dist: ophyd
Requires-Dist: pyzmq
